cyanite.py
cyanite-0.4.6.dist-info/RECORD
cyanite-0.4.6.dist-info/top_level.txt
cyanite-0.4.6.dist-info/WHEEL
cyanite-0.4.6.dist-info/DESCRIPTION.rst
cyanite-0.4.6.dist-info/metadata.json
cyanite-0.4.6.dist-info/METADATA
