Metadata-Version: 2.0
Name: cyanite
Version: 0.4.6
Summary: A plugin for using graphite-web with the cassandra-based Cyanite storage backend
Home-page: https://github.com/brutasse/graphite-cyanite
Author: Bruno Renié
Author-email: bruno@renie.fr
License: BSD
Platform: any
Classifier: Intended Audience :: Developers
Classifier: Intended Audience :: System Administrators
Classifier: License :: OSI Approved :: BSD License
Classifier: Operating System :: OS Independent
Classifier: Programming Language :: Python
Classifier: Programming Language :: Python :: 2
Classifier: Topic :: System :: Monitoring
Requires-Dist: requests
